{"cameraMode":{"drawMode":0,"name":"Shaded","section":"Shading Mode"},"sceneLighting":true,"audioPlay":false,"sceneViewState":{"showFog":true,"showMaterialUpdate":false,"showSkybox":true,"showFlares":true,"showImageEffects":true,"showParticleSystems":true,"showVisualEffectGraphs":true,"m_FxEnabled":true},"in2DMode":false,"pivot":{"x":-14.694087982177735,"y":48.09003448486328,"z":-90.51942443847656},"rotation":{"x":-0.06083809956908226,"y":-0.9294783473014832,"z":0.3171573877334595,"w":-0.17867901921272279},"size":24.923782348632814,"orthographic":false}